flamme_rouge/__init__.py
flamme_rouge/__main__.py
flamme_rouge/__version__.py
flamme_rouge/actions.py
flamme_rouge/cards.py
flamme_rouge/const.py
flamme_rouge/core.py
flamme_rouge/env.py
flamme_rouge/strategies.py
flamme_rouge/teams.py
flamme_rouge/tracks.py
flamme_rouge/utils.py
flamme_rouge-0.1.2.dist-info/LICENSE
flamme_rouge-0.1.2.dist-info/METADATA
flamme_rouge-0.1.2.dist-info/WHEEL
flamme_rouge-0.1.2.dist-info/entry_points.txt
flamme_rouge-0.1.2.dist-info/top_level.txt
flamme_rouge-0.1.2.dist-info/RECORD
